stream_json_parser_utils.cpython-36m-x86_64-linux-gnu.so
streamjsonparser-1.2.dist-info/RECORD
streamjsonparser-1.2.dist-info/LICENSE
streamjsonparser-1.2.dist-info/METADATA
streamjsonparser-1.2.dist-info/WHEEL
streamjsonparser-1.2.dist-info/top_level.txt
test/__init__.py
test/jsontokenizer.py
test/streamdecoder.py
decoder/__init__.py
decoder/streamdecoder.py
tokenizer/__init__.py
tokenizer/jsontokenizer.py
