Metadata-Version: 2.1
Name: streamjsonparser
Version: 1.2
Summary: Stream Json Parser
Home-page: https://github.com/andriylysenko/jsonstreamparser
Author: Andrey Lysenko
Author-email: andrey.lysenko@gmail.com
License: UNKNOWN
Platform: UNKNOWN
